cmu_cpcs_utils.py
cmu_graphics/__init__.py
cmu_graphics/cmu_graphics.py
cmu_graphics/modal.py
cmu_graphics/shape_logic.py
cmu_graphics/utils.py
cmu_graphics/libs/__init__.py
cmu_graphics/libs/cacert.pem
cmu_graphics/libs/loader_util.py
cmu_graphics/libs/webrequest.py
cmu_graphics/meta/version.txt
cmu_graphics/samples/highscore.py
cmu_graphics/samples/pointillism.py
cmu_graphics/samples/puffy.py
cmu_graphics/samples/weather.py
cmu_graphics-1.1.45.dist-info/licenses/LICENSE
cmu_graphics-1.1.45.dist-info/METADATA
cmu_graphics-1.1.45.dist-info/WHEEL
cmu_graphics-1.1.45.dist-info/top_level.txt
cmu_graphics-1.1.45.dist-info/RECORD
