Metadata-Version: 2.4
Name: cmu-graphics
Version: 1.1.45
Summary: The graphics framework used by CMU CS Academy, geared toward beginner CS students.
Author-email: Austin Schick <aschick@andrew.cmu.edu>
License-Expression: BSD-3-Clause
Project-URL: Homepage, https://academy.cs.cmu.edu/
Project-URL: Documentation, https://academy.cs.cmu.edu/docs
Classifier: Programming Language :: Python :: 3
Classifier: Operating System :: OS Independent
Requires-Python: <3.15,>=3.11
License-File: LICENSE
Requires-Dist: pygame-ce>=2
Requires-Dist: pycairo>=1.20
Dynamic: license-file
